fast_llms_txt/__init__.py
fast_llms_txt/generator.py
fast_llms_txt/router.py
fast_llms_txt-0.5.5.dist-info/METADATA
fast_llms_txt-0.5.5.dist-info/WHEEL
fast_llms_txt-0.5.5.dist-info/licenses/LICENSE
fast_llms_txt-0.5.5.dist-info/RECORD
