Metadata-Version: 2.4
Name: fast-llms-txt
Version: 0.5.5
Summary: Generate llms.txt markdown from FastAPI OpenAPI schema for AI agents
Project-URL: Homepage, https://github.com/samaltman/fast-llms-txt
Project-URL: Repository, https://github.com/samaltman/fast-llms-txt
License-Expression: MIT
License-File: LICENSE
Keywords: ai,documentation,fastapi,llms,openapi
Classifier: Development Status :: 4 - Beta
Classifier: Framework :: FastAPI
Classifier: Intended Audience :: Developers
Classifier: License :: OSI Approved :: MIT License
Classifier: Programming Language :: Python :: 3.13
Classifier: Topic :: Documentation
Requires-Python: >=3.11
Requires-Dist: fastapi>=0.128.0
